Cliby.py
linux/build.py
windows/builder.py
windows/preprocessing.py
windows/resources/locator.py
Cliby-1.2.0.dist-info/LICENSE
Cliby-1.2.0.dist-info/METADATA
Cliby-1.2.0.dist-info/WHEEL
Cliby-1.2.0.dist-info/entry_points.txt
Cliby-1.2.0.dist-info/top_level.txt
Cliby-1.2.0.dist-info/RECORD
