Metadata-Version: 2.1
Name: Cliby
Version: 1.2.0
Summary: Simplify C libaries in python
Author-email: Jun Ru Chen <junru.chen.2007@gmail.com>
License: MIT License
Project-URL: Homepage, https://github.com/Shrimp33/Cliby
Keywords: C
Requires-Python: >=3.9
License-File: LICENSE
